Workbook
Name investimento_mensal: Planilha1!$C$18
Name quantos_anos: Planilha1!$C$19
Name rendimento_carteira: Planilha1!$C$13
Name salario: Planilha1!$C$12
Name taxa: Planilha1!$C$20

Sheet Planilha1
B11: CONFIGURAÇÕES
B12: Salário | C12: 4200
B13: Rendimento da carteira | C13: 0.01
B14: Sugestão de investimento | C14: =C12*30% -> 1260
B17: INVESTIMENTO MENSAL
B18: Quanto investir por mês? | C18: 1260
B19: Por quantos anos? | C19: 5
B20: Taxa de rendimento mensal? | C20: 0.01
B21: Quanto de patrimônio acumulado? | C21: =FV(taxa,quantos_anos*12,investimento_mensal*-1) -> 102903.78
B22: Dividendos mensais? | C22: =C21*rendimento_carteira -> 1029.0378
B25: CENÁRIOS | D25: DIVIDENDO
A26: 2 | B26: Quanto em 2 anos? | C26: =FV(taxa,$A26*12,investimento_mensal*-1) -> 33986.566 | D26: =C26*rendimento_carteira -> 339.86566
A27: 5 | B27: Quanto em 5 anos? | C27: =FV(taxa,$A27*12,investimento_mensal*-1) -> 102903.78 | D27: =C27*rendimento_carteira -> 1029.0378
A28: 10 | B28: Quanto em 10 anos? | C28: =FV(taxa,$A28*12,investimento_mensal*-1) -> 289848.75 | D28: =C28*rendimento_carteira -> 2898.4875
A29: 20 | B29: Quanto em 20 anos? | C29: =FV(taxa,$A29*12,investimento_mensal*-1) -> 1246461.8 | D29: =C29*rendimento_carteira -> 12464.618
A30: 30 | B30: Quanto em 30 anos? | C30: =FV(taxa,$A30*12,investimento_mensal*-1) -> 4403654.8 | D30: =C30*rendimento_carteira -> 44036.548
B33: PERFIL | C33: Agressivo
B34: VALOR A SER INVESTIDO POR MÊS | C34: 1260
B37: TIPO DE FII | C37: PERCENTUAL SUGERIDO | D37: VALORES
B38: PAPEL | C38: =VLOOKUP($C$33&"-"&B38,Planilha2!$A:$D,4,) -> 0.5 | D38: =C38*$C$34 -> 630
B39: TIJOLO | C39: =VLOOKUP($C$33&"-"&B39,Planilha2!$A:$D,4,) -> 0.1 | D39: =C39*$C$34 -> 126
B40: HÍBRIDOS | C40: =VLOOKUP($C$33&"-"&B40,Planilha2!$A:$D,4,) -> 0.05 | D40: =C40*$C$34 -> 63
B41: FOFs | C41: =VLOOKUP($C$33&"-"&B41,Planilha2!$A:$D,4,) -> 0.05 | D41: =C41*$C$34 -> 63
B42: DESENVOLVIMENTO | C42: =VLOOKUP($C$33&"-"&B42,Planilha2!$A:$D,4,) -> 0.2 | D42: =C42*$C$34 -> 252
B43: HOTELARIAS | C43: =VLOOKUP($C$33&"-"&B43,Planilha2!$A:$D,4,) -> 0.1 | D43: =C43*$C$34 -> 126
D44: =SUM(D38:D43) -> 1260
B47: Consulte o Tipo de Investimento
B48: PAPEL
B49: =VLOOKUP(B48,Planilha2!K:L,2,) -> • O que são: Não compram imóveis físicos; investem em títulos de renda fixa ligados ao setor imobiliário. • Principais ativos: CRIs (Certificados de Recebíveis Imobiliários) e LCIs (Letras de Crédito Imobiliário). • Fonte de renda: Juros e correção monetária (indexados geralmente ao IPCA, CDI ou IGPM) pagos pelas empresas que emitiram a dívida. • Principais riscos: Risco de crédito (calote do emissor do título) e ausência de garantia do FGC. • Cenário favorável: Alta nas taxas de juros ou momentos de maior inflação.

Sheet Planilha2
A1: CHAVE | B1: PERFIL | C1: TIPO DE FII | D1: % | I1: % | K1: PAPEL | L1: • O que são: Não compram imóveis físicos; investem em títulos de renda fixa ligados ao setor imobiliário. • Principais ativos: CRIs (Certificados de Recebíveis Imobiliários) e LCIs (Letras de Crédito Imobiliário). • Fonte de renda: Juros e correção monetária (indexados geralmente ao IPCA, CDI ou IGPM) pagos pelas empresas que emitiram a dívida. • Principais riscos: Risco de crédito (calote do emissor do título) e ausência de garantia do FGC. • Cenário favorável: Alta nas taxas de juros ou momentos de maior inflação.
A2: Conservador-PAPEL | B2: Conservador | C2: PAPEL | D2: 0.3 | H2: Moderado-TIJOLO | I2: =VLOOKUP(H2,$A:$D,4,) -> 0.4 | K2: TIJOLO | L2: • O que são: Investem diretamente na compra e gestão de imóveis reais. • Principais segmentos: Shoppings centers, galpões logísticos, lajes corporativas (prédios de escritórios), hospitais, hotéis, universidades e supermercados. • Fonte de renda: Aluguéis mensais pagos pelas empresas inquilinas e potencial valorização dos imóveis físicos. • Principais riscos: Vacância (imóvel ficar vazio) e inadimplência dos locatários. • Cenário favorável: Queda nas taxas de juros e expansão econômica.
A3: Conservador-TIJOLO | B3: Conservador | C3: TIJOLO | D3: 0.5 | K3: HÍBRIDOS | L3: • Fundos que misturam as duas estratégias, investindo tanto em imóveis físicos quanto em títulos de papel (recebíveis). • Fonte de renda: Combinação de aluguéis de imóveis e juros de títulos. • Vantagem: Maior flexibilidade para o gestor navegar entre diferentes ciclos econômicos.
A4: Conservador-HÍBRIDOS | B4: Conservador | C4: HÍBRIDOS | D4: 0.1 | K4: FOFs | L4: • O que são: Fundos cuja carteira é composta majoritariamente por cotas de outros FIIs. • Fonte de renda: Dividendos pagos pelos FIIs subjacentes e ganhos com a compra e venda de cotas. • Vantagem: Diversificação instantânea com um único investimento. • Ponto de atenção: O investidor acaba pagando uma "dupla taxa" de administração (a taxa do FoF mais a taxa dos fundos que ele detém).
A5: Conservador-FOFs | B5: Conservador | C5: FOFs | D5: 0.1 | K5: DESENVOLVIMENTO | L5: • Focam na construção e incorporação de novos imóveis para vendê-los ou alugá-los depois de prontos. • Fonte de renda: Lucro com a venda ou locação do empreendimento após o término da obra. • Principais riscos: Atrasos na obra, custos acima do orçamento e risco de mercado no lançamento. • Característica: Costumam não pagar renda mensal nos primeiros anos (fase de obras), mas oferecem potencial de retorno elevado.
A6: Conservador-DESENVOLVIMENTO | B6: Conservador | C6: DESENVOLVIMENTO | D6: 0 | K6: HOTELARIAS | L6: • O que são: O fundo é dono do imóvel físico (prédio do hotel, flats ou resorts). • Fonte de renda: O rendimento do fundo vem do lucro da operação hoteleira. • Proteção contra a inflação: Os hotéis conseguem reajustar o preço das diárias quase em tempo real (diariamente, se necessário) para acompanhar a inflação ou a alta demanda, repassando o ganho rapidamente para o investidor. • Alta Volatilidade (Sazonalidade): É um setor muito cíclico. O fundo costuma lucrar muito em períodos de férias, grandes eventos e feriados, mas pode render bem menos em meses de baixa temporada.
A7: Conservador-HOTELARIAS | B7: Conservador | C7: HOTELARIAS | D7: 0
A8: Moderado-PAPEL | B8: Moderado | C8: PAPEL | D8: 0.32
A9: Moderado-TIJOLO | B9: Moderado | C9: TIJOLO | D9: 0.4
A10: Moderado-HÍBRIDOS | B10: Moderado | C10: HÍBRIDOS | D10: 0.08
A11: Moderado-FOFs | B11: Moderado | C11: FOFs | D11: 0.1
A12: Moderado-DESENVOLVIMENTO | B12: Moderado | C12: DESENVOLVIMENTO | D12: 0.05
A13: Moderado-HOTELARIAS | B13: Moderado | C13: HOTELARIAS | D13: 0.05
A14: Agressivo-PAPEL | B14: Agressivo | C14: PAPEL | D14: 0.5
A15: Agressivo-TIJOLO | B15: Agressivo | C15: TIJOLO | D15: 0.1
A16: Agressivo-HÍBRIDOS | B16: Agressivo | C16: HÍBRIDOS | D16: 0.05
A17: Agressivo-FOFs | B17: Agressivo | C17: FOFs | D17: 0.05
A18: Agressivo-DESENVOLVIMENTO | B18: Agressivo | C18: DESENVOLVIMENTO | D18: 0.2
A19: Agressivo-HOTELARIAS | B19: Agressivo | C19: HOTELARIAS | D19: 0.1
